pyocfl/__init__.py
pyocfl/pyocfl.py
pyocfl/pyocfl_bin.py
pyocfl-0.1.2.dist-info/LICENSE
pyocfl-0.1.2.dist-info/METADATA
pyocfl-0.1.2.dist-info/WHEEL
pyocfl-0.1.2.dist-info/top_level.txt
pyocfl-0.1.2.dist-info/RECORD
